synthetica/__init__.py
synthetica/base.py
synthetica/config.py
synthetica/decorators.py
synthetica/models.py
synthetica/stats.py
python_synthetica-0.1.4.dist-info/LICENSE
python_synthetica-0.1.4.dist-info/METADATA
python_synthetica-0.1.4.dist-info/WHEEL
python_synthetica-0.1.4.dist-info/RECORD
