Metadata-Version: 2.1
Name: python-synthetica
Version: 0.1.4
Summary: Generate synthetic time series data.
Home-page: https://github.com/ActurialCapital/synthetica
License: BSD 3-Clause License
Author: ActurialCapital
Requires-Python: >=3.11,<4.0
Classifier: License :: Other/Proprietary License
Classifier: Programming Language :: Python :: 3
Classifier: Programming Language :: Python :: 3.11
Classifier: Programming Language :: Python :: 3.12
Requires-Dist: numpy (>=1.26.4,<2.0.0)
Requires-Dist: pandas (>=2.2.2,<3.0.0)
Requires-Dist: scipy (>=1.13.1,<2.0.0)
Project-URL: Repository, https://github.com/ActurialCapital/synthetica
